hw4/NAND_gate.vhd
library IEEE;
use IEEE.STD_LOGIC_1164.ALL;

entity NAND_gate is
    Port ( a : in STD_LOGIC;
           b : in STD_LOGIC;
           c : out STD_LOGIC);
end NAND_gate;

architecture Behavioral of NAND_gate is

begin

    c <= not (a and b) after 1 ns;
end Behavioral;

hw4/SR_latch_without_C.vhd
library IEEE;
use IEEE.STD_LOGIC_1164.ALL;

entity SR_latch_without_C is
    Port ( S_bar : in  STD_LOGIC;
        R_bar : in  STD_LOGIC;
        Q     : inout STD_LOGIC;
        Q_bar : inout STD_LOGIC);
end SR_latch_without_C;

architecture Structural of SR_latch_without_C is
    -- Sağlanan NAND_gate bileşeni tanımlanır
    component NAND_gate
    Port ( a : in STD_LOGIC;
        b : in STD_LOGIC;
        c : out STD_LOGIC);
end component;
begin
    -- NAND 1: Q = (S_bar NAND Q_bar)
    U1: NAND_gate port map (a => S_bar, b => Q_bar, c => Q);
    
    -- NAND 2: Q_bar = (R_bar NAND Q)
    U2: NAND_gate port map (a => R_bar, b => Q, c => Q_bar);
end Structural;

hw4/SR_latch_without_C_tb.vhd
library IEEE;
use IEEE.STD_LOGIC_1164.ALL;

entity SR_latch_without_C_tb is
end SR_latch_without_C_tb;

architecture Behavioral of SR_latch_without_C_tb is
    component SR_latch_without_C
    Port ( S_bar, R_bar : in STD_LOGIC;
        Q, Q_bar : inout STD_LOGIC);
end component;

signal S_bar, R_bar : STD_LOGIC := '1';
signal Q, Q_bar : STD_LOGIC;
begin
    uut: SR_latch_without_C port map (S_bar => S_bar, R_bar => R_bar, Q => Q, Q_bar => Q_bar);

    stim_proc: process
    begin
        wait for 20 ns;
        S_bar <= '0'; R_bar <= '1'; -- Set
        wait for 20 ns;
        S_bar <= '1'; R_bar <= '1'; -- Hold
        wait for 20 ns;
        S_bar <= '1'; R_bar <= '0'; -- Reset
        wait for 20 ns;
        S_bar <= '1'; R_bar <= '1'; -- Hold
        wait;
    end process;
end Behavioral;

hw4/wave_SR_no_C.vcd
$date
  Tue Dec 23 13:45:55 2025
$end
$version
  GHDL v0
$end
$timescale
  1 fs
$end
$scope module standard $end
$upscope $end
$scope module std_logic_1164 $end
$upscope $end
$scope module sr_latch_without_c_tb $end
$var reg 1 ! s_bar $end
$var reg 1 " r_bar $end
$var reg 1 # q $end
$var reg 1 $ q_bar $end
$scope module uut $end
$var reg 1 % s_bar $end
$var reg 1 & r_bar $end
$var reg 1 ' q $end
$var reg 1 ( q_bar $end
$scope module u1 $end
$var reg 1 ) a $end
$var reg 1 * b $end
$var reg 1 + c $end
$upscope $end
$scope module u2 $end
$var reg 1 , a $end
$var reg 1 - b $end
$var reg 1 . c $end
$upscope $end
$upscope $end
$upscope $end
$enddefinitions $end
#0
1!
1"
U#
U$
1%
1&
U'
U(
1)
U*
U+
1,
U-
U.
#1000000
U+
U.
#20000000
0!
0%
0)
#21000000
1#
1'
1+
1-
#22000000
0$
0(
0*
0.
#23000000
1+
#40000000
1!
1%
1)
#41000000
1+
#60000000
0"
0&
0,
#61000000
1$
1(
1*
1.
#62000000
0#
0'
0+
0-
#63000000
1.
#80000000
1"
1&
1,
#81000000
1.
