hw4/NAND_gate.vhd
library IEEE;
use IEEE.STD_LOGIC_1164.ALL;

entity NAND_gate is
    Port ( a : in STD_LOGIC;
           b : in STD_LOGIC;
           c : out STD_LOGIC);
end NAND_gate;

architecture Behavioral of NAND_gate is

begin

    c <= not (a and b) after 1 ns;
end Behavioral;

hw4/SR_latch_without_C.vhd
library IEEE;
use IEEE.STD_LOGIC_1164.ALL;

entity SR_latch_without_C is
    Port ( S_bar : in  STD_LOGIC;
        R_bar : in  STD_LOGIC;
        Q     : inout STD_LOGIC;
        Q_bar : inout STD_LOGIC);
end SR_latch_without_C;

architecture Structural of SR_latch_without_C is
    -- Sağlanan NAND_gate bileşeni tanımlanır
    component NAND_gate
    Port ( a : in STD_LOGIC;
        b : in STD_LOGIC;
        c : out STD_LOGIC);
end component;
begin
    -- NAND 1: Q = (S_bar NAND Q_bar)
    U1: NAND_gate port map (a => S_bar, b => Q_bar, c => Q);
    
    -- NAND 2: Q_bar = (R_bar NAND Q)
    U2: NAND_gate port map (a => R_bar, b => Q, c => Q_bar);
end Structural;

hw4/SR_latch.vhd
library IEEE;
use IEEE.STD_LOGIC_1164.ALL;

entity SR_latch is
    Port ( S : in  STD_LOGIC;
        R : in  STD_LOGIC;
        C : in  STD_LOGIC; -- Control / Enable
        Q : inout STD_LOGIC;
        Q_bar : inout STD_LOGIC);
end SR_latch;

architecture Structural of SR_latch is
    component NAND_gate
    Port ( a, b : in STD_LOGIC; c : out STD_LOGIC);
end component;

component SR_latch_without_C
Port ( S_bar, R_bar : in STD_LOGIC; Q, Q_bar : inout STD_LOGIC);
end component;

signal s_nand_out, r_nand_out : STD_LOGIC;
begin
    -- Giriş Kontrol Mantığı (NAND Gates)
    NAND1: NAND_gate port map (a => S, b => C, c => s_nand_out);
    NAND2: NAND_gate port map (a => R, b => C, c => r_nand_out);

    -- Çekirdek Latch Çağrısı
    Core_Latch: SR_latch_without_C port map (
        S_bar => s_nand_out,
        R_bar => r_nand_out,
        Q => Q,
        Q_bar => Q_bar
    );
end Structural;

hw4/D_latch.vhd
library IEEE;
use IEEE.STD_LOGIC_1164.ALL;

entity D_latch is
    Port ( D : in  STD_LOGIC;
        C : in  STD_LOGIC;
        Q : inout STD_LOGIC;
        Q_bar : inout STD_LOGIC);
end D_latch;

architecture Structural of D_latch is
    component SR_latch
    Port ( S, R, C : in STD_LOGIC; Q, Q_bar : inout STD_LOGIC);
end component;

component NAND_gate
Port ( a, b : in STD_LOGIC; c : out STD_LOGIC);
end component;

signal not_D : STD_LOGIC;
begin
    -- Inverter: D NAND D = NOT D
    Inv1: NAND_gate port map (a => D, b => D, c => not_D);

    U_SR: SR_latch port map (
        S => D,
        R => not_D,
        C => C,
        Q => Q,
        Q_bar => Q_bar
    );
end Structural;

hw4/D_latch_tb.vhd
library IEEE;
use IEEE.STD_LOGIC_1164.ALL;

entity D_latch_tb is
end D_latch_tb;

architecture Behavioral of D_latch_tb is
    component D_latch
    Port ( D, C : in STD_LOGIC; Q, Q_bar : inout STD_LOGIC);
end component;
signal D, C : STD_LOGIC := '0';
signal Q, Q_bar : STD_LOGIC;
begin
    uut: D_latch port map (D, C, Q, Q_bar);
    process begin
        C <= '1'; D <= '1'; wait for 20 ns; -- Transparent High
        C <= '1'; D <= '0'; wait for 20 ns; -- Transparent Low
        C <= '0'; D <= '1'; wait for 20 ns; -- Latch (Hold previous 0)
        wait;
    end process;
end Behavioral;

hw4/wave_D_latch.vcd
$date
  Tue Dec 23 13:45:55 2025
$end
$version
  GHDL v0
$end
$timescale
  1 fs
$end
$scope module standard $end
$upscope $end
$scope module std_logic_1164 $end
$upscope $end
$scope module d_latch_tb $end
$var reg 1 ! d $end
$var reg 1 " c $end
$var reg 1 # q $end
$var reg 1 $ q_bar $end
$scope module uut $end
$var reg 1 % d $end
$var reg 1 & c $end
$var reg 1 ' q $end
$var reg 1 ( q_bar $end
$var reg 1 ) not_d $end
$scope module inv1 $end
$var reg 1 * a $end
$var reg 1 + b $end
$var reg 1 , c $end
$upscope $end
$scope module u_sr $end
$var reg 1 - s $end
$var reg 1 . r $end
$var reg 1 / c $end
$var reg 1 0 q $end
$var reg 1 1 q_bar $end
$var reg 1 2 s_nand_out $end
$var reg 1 3 r_nand_out $end
$scope module nand1 $end
$var reg 1 4 a $end
$var reg 1 5 b $end
$var reg 1 6 c $end
$upscope $end
$scope module nand2 $end
$var reg 1 7 a $end
$var reg 1 8 b $end
$var reg 1 9 c $end
$upscope $end
$scope module core_latch $end
$var reg 1 : s_bar $end
$var reg 1 ; r_bar $end
$var reg 1 < q $end
$var reg 1 = q_bar $end
$scope module u1 $end
$var reg 1 > a $end
$var reg 1 ? b $end
$var reg 1 @ c $end
$upscope $end
$scope module u2 $end
$var reg 1 A a $end
$var reg 1 B b $end
$var reg 1 C c $end
$upscope $end
$upscope $end
$upscope $end
$upscope $end
$upscope $end
$enddefinitions $end
#0
1!
1"
U#
U$
1%
1&
U'
U(
U)
1*
1+
U,
1-
U.
1/
U0
U1
U2
U3
14
15
U6
U7
18
U9
U:
U;
U<
U=
U>
U?
U@
UA
UB
UC
#1000000
0)
0,
0.
02
06
07
U9
0:
0>
U@
UC
#2000000
1#
1'
10
13
19
1;
1<
1@
1A
1B
#3000000
0$
0(
01
0=
0?
0C
#4000000
1@
#20000000
0!
0%
0*
0+
0-
04
#21000000
1)
1,
1.
12
16
17
1:
1>
#22000000
03
09
0;
1@
0A
#23000000
1$
1(
11
1=
1?
1C
#24000000
0#
0'
00
0<
0@
0B
#25000000
1C
#40000000
1!
0"
1%
0&
1*
1+
1-
0/
14
05
08
#41000000
0)
0,
0.
13
16
07
19
1;
1A
#42000000
19
1C
