hw4/NAND_gate.vhd
library IEEE;
use IEEE.STD_LOGIC_1164.ALL;

entity NAND_gate is
    Port ( a : in STD_LOGIC;
           b : in STD_LOGIC;
           c : out STD_LOGIC);
end NAND_gate;

architecture Behavioral of NAND_gate is

begin

    c <= not (a and b) after 1 ns;
end Behavioral;

hw4/SR_latch_without_C.vhd
library IEEE;
use IEEE.STD_LOGIC_1164.ALL;

entity SR_latch_without_C is
    Port ( S_bar : in  STD_LOGIC;
        R_bar : in  STD_LOGIC;
        Q     : inout STD_LOGIC;
        Q_bar : inout STD_LOGIC);
end SR_latch_without_C;

architecture Structural of SR_latch_without_C is
    -- Sağlanan NAND_gate bileşeni tanımlanır
    component NAND_gate
    Port ( a : in STD_LOGIC;
        b : in STD_LOGIC;
        c : out STD_LOGIC);
end component;
begin
    -- NAND 1: Q = (S_bar NAND Q_bar)
    U1: NAND_gate port map (a => S_bar, b => Q_bar, c => Q);
    
    -- NAND 2: Q_bar = (R_bar NAND Q)
    U2: NAND_gate port map (a => R_bar, b => Q, c => Q_bar);
end Structural;

hw4/SR_latch.vhd
library IEEE;
use IEEE.STD_LOGIC_1164.ALL;

entity SR_latch is
    Port ( S : in  STD_LOGIC;
        R : in  STD_LOGIC;
        C : in  STD_LOGIC; -- Control / Enable
        Q : inout STD_LOGIC;
        Q_bar : inout STD_LOGIC);
end SR_latch;

architecture Structural of SR_latch is
    component NAND_gate
    Port ( a, b : in STD_LOGIC; c : out STD_LOGIC);
end component;

component SR_latch_without_C
Port ( S_bar, R_bar : in STD_LOGIC; Q, Q_bar : inout STD_LOGIC);
end component;

signal s_nand_out, r_nand_out : STD_LOGIC;
begin
    -- Giriş Kontrol Mantığı (NAND Gates)
    NAND1: NAND_gate port map (a => S, b => C, c => s_nand_out);
    NAND2: NAND_gate port map (a => R, b => C, c => r_nand_out);

    -- Çekirdek Latch Çağrısı
    Core_Latch: SR_latch_without_C port map (
        S_bar => s_nand_out,
        R_bar => r_nand_out,
        Q => Q,
        Q_bar => Q_bar
    );
end Structural;

hw4/SR_latch_tb.vhd
library IEEE;
use IEEE.STD_LOGIC_1164.ALL;

entity SR_latch_tb is
end SR_latch_tb;

architecture Behavioral of SR_latch_tb is
    component SR_latch
    Port ( S, R, C : in STD_LOGIC; Q, Q_bar : inout STD_LOGIC);
end component;
signal S, R, C : STD_LOGIC := '0';
signal Q, Q_bar : STD_LOGIC;
begin
    uut: SR_latch port map (S, R, C, Q, Q_bar);
    process begin
        C <= '1'; S <= '1'; R <= '0'; wait for 20 ns; -- Set
        C <= '0'; S <= '0'; R <= '0'; wait for 20 ns; -- Hold (C=0)
        C <= '1'; S <= '0'; R <= '1'; wait for 20 ns; -- Reset
        wait;
    end process;
end Behavioral;

hw4/wave_SR.vcd
$date
  Tue Dec 23 13:45:55 2025
$end
$version
  GHDL v0
$end
$timescale
  1 fs
$end
$scope module standard $end
$upscope $end
$scope module std_logic_1164 $end
$upscope $end
$scope module sr_latch_tb $end
$var reg 1 ! s $end
$var reg 1 " r $end
$var reg 1 # c $end
$var reg 1 $ q $end
$var reg 1 % q_bar $end
$scope module uut $end
$var reg 1 & s $end
$var reg 1 ' r $end
$var reg 1 ( c $end
$var reg 1 ) q $end
$var reg 1 * q_bar $end
$var reg 1 + s_nand_out $end
$var reg 1 , r_nand_out $end
$scope module nand1 $end
$var reg 1 - a $end
$var reg 1 . b $end
$var reg 1 / c $end
$upscope $end
$scope module nand2 $end
$var reg 1 0 a $end
$var reg 1 1 b $end
$var reg 1 2 c $end
$upscope $end
$scope module core_latch $end
$var reg 1 3 s_bar $end
$var reg 1 4 r_bar $end
$var reg 1 5 q $end
$var reg 1 6 q_bar $end
$scope module u1 $end
$var reg 1 7 a $end
$var reg 1 8 b $end
$var reg 1 9 c $end
$upscope $end
$scope module u2 $end
$var reg 1 : a $end
$var reg 1 ; b $end
$var reg 1 < c $end
$upscope $end
$upscope $end
$upscope $end
$upscope $end
$enddefinitions $end
#0
1!
0"
1#
U$
U%
1&
0'
1(
U)
U*
U+
U,
1-
1.
U/
00
11
U2
U3
U4
U5
U6
U7
U8
U9
U:
U;
U<
#1000000
0+
1,
0/
12
03
14
07
U9
1:
U<
#2000000
1$
1)
15
19
1;
U<
#3000000
0%
0*
06
08
0<
#4000000
19
#20000000
0!
0#
0&
0(
0-
0.
01
#21000000
1+
1/
12
13
17
#22000000
19
#40000000
1"
1#
1'
1(
1.
10
11
#41000000
0,
1/
02
04
0:
#42000000
1%
1*
16
18
1<
#43000000
0$
0)
05
09
0;
#44000000
1<
