hw3/full_adder.vhd
library IEEE;
use IEEE.STD_LOGIC_1164.ALL;

entity FULL_ADDER is
    Port ( A : in  STD_LOGIC;
        B : in  STD_LOGIC;
        Cin : in  STD_LOGIC; -- Carry In
        S : out STD_LOGIC; -- Sum
        Cout : out STD_LOGIC); -- Carry Out
end FULL_ADDER;

architecture Dataflow of FULL_ADDER is
begin
    -- Dataflow Modeling
    -- Toplam (S) için denklem: A XOR B XOR Cin
    S <= A xor B xor Cin;
    
    -- Elde (Cout) için sadeleştirilmiş denklem: (A AND B) OR (A AND Cin) OR (B AND Cin)
    Cout <= (A and B) or (A and Cin) or (B and Cin);
end Dataflow;

hw3/full_adder_tb.vhd
library IEEE;
use IEEE.STD_LOGIC_1164.ALL;

-- Testbench Varlığı
entity FULL_ADDER_TB is
end FULL_ADDER_TB;

architecture Behavioral of FULL_ADDER_TB is
    -- Test edilecek bileşenin (FA) tanımlanması
    component FULL_ADDER
    Port ( A : in  STD_LOGIC;
        B : in  STD_LOGIC;
        Cin : in  STD_LOGIC;
        S : out STD_LOGIC;
        Cout : out STD_LOGIC);
end component;

    -- Sinyal tanımlamaları
signal A_TB, B_TB, Cin_TB : STD_LOGIC := '0';
signal S_TB, Cout_TB : STD_LOGIC;

    -- Zaman sabiti
constant Clock_Period : time := 10 ns;

begin
    -- Test edilecek bileşenin bağlanması (Instance)
    uut: FULL_ADDER
    port map (
        A => A_TB,
        B => B_TB,
        Cin => Cin_TB,
        S => S_TB,
        Cout => Cout_TB
    );

    -- Giriş Vektörlerini Üreten İşlem (Stimulus)
    stim_proc: process
    begin
        -- Tüm 8 kombinasyonu sırayla uygula (000'dan 111'e)
        
        -- 0. A=0, B=0, Cin=0
        wait for Clock_Period;

        -- 1. A=0, B=0, Cin=1
        Cin_TB <= '1';
        wait for Clock_Period;
        
        -- 2. A=0, B=1, Cin=0
        B_TB <= '1';
        Cin_TB <= '0';
        wait for Clock_Period;

        -- 3. A=0, B=1, Cin=1
        Cin_TB <= '1';
        wait for Clock_Period;

        -- 4. A=1, B=0, Cin=0
        A_TB <= '1';
        B_TB <= '0';
        Cin_TB <= '0';
        wait for Clock_Period;

        -- 5. A=1, B=0, Cin=1
        Cin_TB <= '1';
        wait for Clock_Period;

        -- 6. A=1, B=1, Cin=0
        B_TB <= '1';
        Cin_TB <= '0';
        wait for Clock_Period;
        
        -- 7. A=1, B=1, Cin=1
        Cin_TB <= '1';
        wait for Clock_Period;

        -- Simülasyonu sonlandır
        wait;
    end process;
end Behavioral;

hw3/full_adder_tb.vcd
$date
  Sun Nov 23 22:51:34 2025
$end
$version
  GHDL v0
$end
$timescale
  1 fs
$end
$scope module standard $end
$upscope $end
$scope module std_logic_1164 $end
$upscope $end
$scope module full_adder_tb $end
$var reg 1 ! a_tb $end
$var reg 1 " b_tb $end
$var reg 1 # cin_tb $end
$var reg 1 $ s_tb $end
$var reg 1 % cout_tb $end
$scope module uut $end
$var reg 1 & a $end
$var reg 1 ' b $end
$var reg 1 ( cin $end
$var reg 1 ) s $end
$var reg 1 * cout $end
$upscope $end
$upscope $end
$enddefinitions $end
#0
0!
0"
0#
0$
0%
0&
0'
0(
0)
0*
#10000000
1#
1$
1(
1)
#20000000
1"
0#
1'
0(
#30000000
1#
0$
1%
1(
0)
1*
#40000000
1!
0"
0#
1$
0%
1&
0'
0(
1)
0*
#50000000
1#
0$
1%
1(
0)
1*
#60000000
1"
0#
1'
0(
#70000000
1#
1$
1(
1)
